blackbear_media_scoring/__init__.py
blackbear_media_scoring/__main__.py
blackbear_media_scoring/assesor/__init__.py
blackbear_media_scoring/assesor/__main__.py
blackbear_media_scoring/assesor/assess.py
blackbear_media_scoring/assesor/prompts.py
blackbear_media_scoring/assesor/provider/gemini.py
blackbear_media_scoring/assesor/provider/llm.py
blackbear_media_scoring/assesor/provider/openrouter.py
blackbear_media_scoring/downloader/__init__.py
blackbear_media_scoring/downloader/__main__.py
blackbear_media_scoring/downloader/downloader.py
blackbear_media_scoring/downloader/service/youtube.py
blackbear_media_scoring/downloader/time_utils.py
blackbear_media_scoring/extractor/__init__.py
blackbear_media_scoring/extractor/__main__.py
blackbear_media_scoring/extractor/extract.py
blackbear_media_scoring/extractor/prompts.py
blackbear_media_scoring/extractor/provider/__init__.py
blackbear_media_scoring/extractor/provider/gemini.py
blackbear_media_scoring/extractor/provider/openrouter.py
blackbear_media_scoring/extractor/provider/provider.py
blackbear_media_scoring/extractor/video_utils.py
blackbear_media_scoring/utils/__init__.py
blackbear_media_scoring/utils/cost_calculator.py
blackbear_media_scoring-0.1.5.dist-info/METADATA
blackbear_media_scoring-0.1.5.dist-info/WHEEL
blackbear_media_scoring-0.1.5.dist-info/entry_points.txt
blackbear_media_scoring-0.1.5.dist-info/RECORD
