Metadata-Version: 2.4
Name: blackbear_media_scoring
Version: 0.1.5
Summary: LLM-based automated media scoring
Author: Rivo Juicer Wowor
Author-email: rivo@mobilepulsa.com
Requires-Python: >=3.9
Classifier: Programming Language :: Python :: 3
Classifier: Programming Language :: Python :: 3.9
Classifier: Programming Language :: Python :: 3.10
Classifier: Programming Language :: Python :: 3.11
Classifier: Programming Language :: Python :: 3.12
Classifier: Programming Language :: Python :: 3.13
Classifier: Programming Language :: Python :: 3.14
Provides-Extra: dev
Requires-Dist: ffmpeg-python
Requires-Dist: google-genai
Requires-Dist: litellm
Requires-Dist: pillow
Requires-Dist: pytest ; extra == "dev"
Requires-Dist: python-dotenv
Requires-Dist: ruff ; extra == "dev"
Requires-Dist: yt-dlp
